mdformat_ruff/__init__.py
mdformat_ruff/py.typed
mdformat_ruff-0.1.2.dist-info/LICENSE
mdformat_ruff-0.1.2.dist-info/METADATA
mdformat_ruff-0.1.2.dist-info/WHEEL
mdformat_ruff-0.1.2.dist-info/entry_points.txt
mdformat_ruff-0.1.2.dist-info/RECORD
