Metadata-Version: 2.1
Name: mdformat-ruff
Version: 0.1.2
Summary: Mdformat plugin to ruffen Python code blocks
Home-page: https://github.com/Freed-Wu/mdformat-ruff
License: MIT
Keywords: mdformat,markdown,commonmark,formatter
Author: Wu Zhenyu
Author-email: wuzhenyu@ustc.edu
Requires-Python: >=3.7,<4.0
Classifier: License :: OSI Approved :: MIT License
Classifier: Programming Language :: Python :: 3
Classifier: Programming Language :: Python :: 3.7
Classifier: Programming Language :: Python :: 3.8
Classifier: Programming Language :: Python :: 3.9
Classifier: Programming Language :: Python :: 3.10
Classifier: Programming Language :: Python :: 3.11
Classifier: Programming Language :: Python :: 3.12
Classifier: Topic :: Documentation
Classifier: Topic :: Text Processing :: Markup
Classifier: Typing :: Typed
Requires-Dist: ruff
Project-URL: Bug Report, https://github.com/Freed-Wu/mdformat-ruff/issues
Project-URL: Download, https://github.com/Freed-Wu/mdformat-ruff/releases
Project-URL: Homepage, https://mdformat-ruff.readthedocs.io
Project-URL: Repository, https://github.com/Freed-Wu/mdformat-ruff
Project-URL: Source, https://github.com/Freed-Wu/mdformat-ruff
